pyname_shifter/__init__.py
pyname_shifter/main.py
PyNameShifter-1.0.1.dist-info/METADATA
PyNameShifter-1.0.1.dist-info/WHEEL
PyNameShifter-1.0.1.dist-info/entry_points.txt
PyNameShifter-1.0.1.dist-info/top_level.txt
PyNameShifter-1.0.1.dist-info/RECORD
