Metadata-Version: 2.1
Name: PyNameShifter
Version: 1.0.1
Summary: A simple tool for renaming files and folders.
Home-page: https://github.com/dam-ari/PyNameShifter
Author: BarBur 🦢
Author-email: 
